mitosheet/__init__.py
mitosheet/__main__.py
mitosheet/_frontend.py
mitosheet/_version.py
mitosheet/array_utils.py
mitosheet/column_headers.py
mitosheet/dataframe_display_formatters.py
mitosheet/errors.py
mitosheet/excel_utils.py
mitosheet/hello.py
mitosheet/is_type_utils.py
mitosheet/kernel_utils.py
mitosheet/mito_backend.py
mitosheet/mito_frontend.css
mitosheet/mito_frontend.js
mitosheet/parser.py
mitosheet/save_paths.py
mitosheet/selection_utils.py
mitosheet/state.py
mitosheet/step.py
mitosheet/steps_manager.py
mitosheet/types.py
mitosheet/utils.py
mitosheet/ai/__init__.py
mitosheet/ai/ai_utils.py
mitosheet/ai/prompt.py
mitosheet/ai/recon.py
mitosheet/api/__init__.py
mitosheet/api/api.py
mitosheet/api/get_ai_completion.py
mitosheet/api/get_all_params_for_step_type.py
mitosheet/api/get_available_snowflake_options_and_defaults.py
mitosheet/api/get_code_snippets.py
mitosheet/api/get_column_describe.py
mitosheet/api/get_column_summary_graph.py
mitosheet/api/get_csv_files_metadata.py
mitosheet/api/get_dataframe_as_csv.py
mitosheet/api/get_dataframe_as_excel.py
mitosheet/api/get_defined_df_names.py
mitosheet/api/get_excel_file_metadata.py
mitosheet/api/get_imported_files_and_dataframes_from_analysis_name.py
mitosheet/api/get_imported_files_and_dataframes_from_current_steps.py
mitosheet/api/get_parameterizable_params.py
mitosheet/api/get_params.py
mitosheet/api/get_path_contents.py
mitosheet/api/get_path_join.py
mitosheet/api/get_pr_url_of_new_pr.py
mitosheet/api/get_render_count.py
mitosheet/api/get_saved_analysis_code.py
mitosheet/api/get_search_matches.py
mitosheet/api/get_split_text_to_columns_preview.py
mitosheet/api/get_test_imports.py
mitosheet/api/get_unique_value_counts.py
mitosheet/api/get_validate_snowflake_credentials.py
mitosheet/code_chunks/__init__.py
mitosheet/code_chunks/add_column_set_formula_code_chunk.py
mitosheet/code_chunks/ai_transformation_code_chunk.py
mitosheet/code_chunks/code_chunk.py
mitosheet/code_chunks/code_chunk_utils.py
mitosheet-0.2.59.dist-info/LICENSE.txt
mitosheet-0.2.59.dist-info/METADATA
mitosheet-0.2.59.dist-info/WHEEL
mitosheet-0.2.59.dist-info/top_level.txt
mitosheet-0.2.59.dist-info/RECORD
