Metadata-Version: 2.1
Name: mitosheet
Version: 0.2.59
Summary: The Mito Spreadsheet
Home-page: https://github.com/mito-ds/mito
Author: Mito Sheet
Author-email: aaron@sagacollab.com
License: GNU Affero General Public License v3
Project-URL: Homepage, https://github.com/mito-ds/mito
Project-URL: Repository, https://github.com/mito-ds/mito
Project-URL: Issues, https://github.com/mito-ds/mito/issues
Platform: Linux
Platform: Mac OS X
Platform: Windows
Classifier: License :: OSI Approved :: GNU Affero General Public License v3
Classifier: Programming Language :: Python
Classifier: Programming Language :: Python :: 3
Classifier: Programming Language :: Python :: 3.9
Classifier: Programming Language :: Python :: 3.10
Classifier: Programming Language :: Python :: 3.11
Classifier: Programming Language :: Python :: 3.12
Classifier: Programming Language :: Python :: 3.13
Classifier: Framework :: Jupyter
Classifier: Framework :: Jupyter :: JupyterLab
Classifier: Framework :: Jupyter :: JupyterLab :: 4
Classifier: Framework :: Jupyter :: JupyterLab :: Extensions
Classifier: Framework :: Jupyter :: JupyterLab :: Extensions :: Prebuilt
Requires-Python: >=3.9
Provides-Extra: test
Provides-Extra: deploy
Provides-Extra: streamlit
Provides-Extra: optional_feature_dependencies
License-File: LICENSE.txt
